gpcontext_maker/__init__.py
gpcontext_maker/__main__.py
gpcontext_maker/default_gpcontext_ignore.txt
gpcontext_maker-1.5.0.dist-info/METADATA
gpcontext_maker-1.5.0.dist-info/WHEEL
gpcontext_maker-1.5.0.dist-info/RECORD
