Metadata-Version: 2.1
Name: gpcontext-maker
Version: 1.5.0
Summary: Generate a context file of your whole software project to feed into a LLM like ChatGPT
Home-page: https://github.com/estill01/ChatGPContextMaker
License: MIT
Author: estill01
Author-email: ehs.stillman@gmail.com
Requires-Python: >=3.9,<4.0
Classifier: License :: OSI Approved :: MIT License
Classifier: Programming Language :: Python :: 3
Classifier: Programming Language :: Python :: 3.9
Classifier: Programming Language :: Python :: 3.10
Classifier: Programming Language :: Python :: 3.11
Requires-Dist: argparse (>=1.4.0,<2.0.0)
Requires-Dist: pathlib (>=1.0.1,<2.0.0)
Requires-Dist: pyperclip (>=1.8.2,<2.0.0)
